fladrif/__init__.py
fladrif/apply.py
fladrif/py.typed
fladrif/treediff.py
fladrif-0.2.0.dist-info/METADATA
fladrif-0.2.0.dist-info/WHEEL
fladrif-0.2.0.dist-info/RECORD
