Metadata-Version: 2.1
Name: fladrif
Version: 0.2.0
Summary: Compute a series of operations to transform one tree into another
License: GPL-2.0-or-later
Author: Sam Wilson
Author-email: sam@binarycake.ca
Requires-Python: >=3.10,<4.0
Classifier: License :: OSI Approved :: GNU General Public License v2 or later (GPLv2+)
Classifier: Programming Language :: Python :: 3
Classifier: Programming Language :: Python :: 3.10
Classifier: Programming Language :: Python :: 3.11
